AM_project1/__init__.py
AM_project1/grid_utils.py
AM_project1/helpers.py
AM_project1/matching.py
AM_project1/objects.py
AM_project1/phase_correlation.py
AM_project1/tracks.py
AM_project1/version.py
AM_project1-0.0.2.dist-info/METADATA
AM_project1-0.0.2.dist-info/WHEEL
AM_project1-0.0.2.dist-info/top_level.txt
AM_project1-0.0.2.dist-info/RECORD
